squerly/__init__.py
squerly/boolean.py
squerly/query.py
squerly/tests/__init__.py
squerly/tests/test_find.py
squerly/tests/test_keys.py
squerly/tests/test_parents.py
squerly/tests/test_query.py
squerly/tests/test_upto.py
squerly/tests/test_where.py
squerly/tests/test_where_boolean.py
squerly-0.2.2.dist-info/LICENSE
squerly-0.2.2.dist-info/METADATA
squerly-0.2.2.dist-info/WHEEL
squerly-0.2.2.dist-info/top_level.txt
squerly-0.2.2.dist-info/RECORD
