Metadata-Version: 2.1
Name: squerly
Version: 0.2.2
Summary: Squerly takes the tedium out of nested dicts and lists.
Home-page: https://github.com/csams/squerly
Author: Christopher Sams
Author-email: csams@gmail.com
License: Apache 2.0
Platform: UNKNOWN
Classifier: Development Status :: 3 - Alpha
Classifier: Intended Audience :: Developers
Classifier: Natural Language :: English
Classifier: License :: OSI Approved :: Apache Software License
Classifier: Programming Language :: Python
Classifier: Programming Language :: Python :: 2.7
Classifier: Programming Language :: Python :: 3.6
Classifier: Programming Language :: Python :: 3.7
Classifier: Programming Language :: Python :: 3.8
Requires-Dist: pyyaml
Provides-Extra: develop
Requires-Dist: twine ; extra == 'develop'
Requires-Dist: pytest ; extra == 'develop'
Requires-Dist: pandas ; extra == 'develop'
Requires-Dist: flake8 ; extra == 'develop'
Requires-Dist: pytest-cov ; extra == 'develop'
Requires-Dist: setuptools ; extra == 'develop'
Requires-Dist: Sphinx ; extra == 'develop'
Requires-Dist: IPython ; extra == 'develop'
Requires-Dist: sphinx-rtd-theme ; extra == 'develop'
Requires-Dist: coverage ; extra == 'develop'
Requires-Dist: wheel ; extra == 'develop'
Provides-Extra: docs
Requires-Dist: Sphinx ; extra == 'docs'
Requires-Dist: sphinx-rtd-theme ; extra == 'docs'
Provides-Extra: optional
Requires-Dist: IPython ; extra == 'optional'
Requires-Dist: pandas ; extra == 'optional'
